{
  "version": 3,
  "middleware": {
    "/": {
      "files": [
        "server/edge-runtime-webpack.js",
        "server/middleware.js"
      ],
      "name": "middleware",
      "page": "/",
      "matchers": [
        {
          "regexp": "^(?:\\/(_next\\/data\\/[^/]{1,}))?\\/admin(?:\\/((?:[^\\/#\\?]+?)(?:\\/(?:[^\\/#\\?]+?))*))?(.json)?[\\/#\\?]?$",
          "originalSource": "/admin/:path*"
        }
      ],
      "wasm": [],
      "assets": [],
      "env": {
        "__NEXT_BUILD_ID": "mdaq_MGS6nvF25nlz2urw",
        "NEXT_SERVER_ACTIONS_ENCRYPTION_KEY": "7znrMLHOT8BQs0bE2zDhsYxM/qd5HJUTVWRLIs2M+1Y=",
        "__NEXT_PREVIEW_MODE_ID": "2b2bd7a66fb0430d8ceb3b8ce42d3782",
        "__NEXT_PREVIEW_MODE_ENCRYPTION_KEY": "006096d8484269362221c819b492a5638ab30052747598662255af55fc8559d0",
        "__NEXT_PREVIEW_MODE_SIGNING_KEY": "9ad4e82e3adc2cde6fd79b3b6f7ee3cc07e34d2a44b5ea27654ac338704f3f6b"
      }
    }
  },
  "functions": {},
  "sortedMiddleware": [
    "/"
  ]
}